publish/__init__.py
publish/cli.py
publish/cloudflare.py
publish/config.py
publish/exceptions.py
publish/helpers.py
publish/http.py
publish/publishing.py
ipfs_publish-0.2.1.dist-info/AUTHORS
ipfs_publish-0.2.1.dist-info/LICENSE
ipfs_publish-0.2.1.dist-info/METADATA
ipfs_publish-0.2.1.dist-info/WHEEL
ipfs_publish-0.2.1.dist-info/entry_points.txt
ipfs_publish-0.2.1.dist-info/pbr.json
ipfs_publish-0.2.1.dist-info/top_level.txt
ipfs_publish-0.2.1.dist-info/RECORD
