Metadata-Version: 2.1
Name: ipfs-publish
Version: 0.2.1
Summary: CD-like tool for publishing your static website from Git to IPFS
Home-page: https://ipfs-publish.uhlir.dev
Author: Adam Uhlir
Author-email: adam@uhlir.dev
License: MIT
Project-URL: Source, https://github.com/AuHau/ipfs-publish
Platform: UNKNOWN
Classifier: License :: OSI Approved :: MIT License
Classifier: Programming Language :: Python
Classifier: Programming Language :: Python :: 3
Classifier: Programming Language :: Python :: 3.7
Classifier: Programming Language :: Python :: 3.8
Classifier: Programming Language :: Python :: Implementation :: CPython
Classifier: Development Status :: 4 - Beta
Classifier: Intended Audience :: Developers
Requires-Python: >=3.7.0, <3.9.0
Requires-Dist: gitpython (==3.1.9)
Requires-Dist: click (==7.1.2)
Requires-Dist: click-completion (==0.5.2)
Requires-Dist: inquirer (==2.7.0)
Requires-Dist: pbr (==5.4.4)
Requires-Dist: quart (==0.13.1)
Requires-Dist: ipfshttpclient (==0.6.1)
Requires-Dist: toml (==0.10.1)
Requires-Dist: appdirs (==1.4.4)
Requires-Dist: cloudflare (==2.8.13)
